{"items":[{"verified":false,"w":2,"h":3,"icon":"https://web.poecdn.com/gen/image/WzI1LDE0LHsiZiI6IjJESXRlbXMvQXJtb3Vycy9Cb2R5QXJtb3Vycy9CbHVuZGVyYm9yZSIsInciOjIsImgiOjMsInNjYWxlIjoxfV0/4b34ebf3fe/Blunderbore.png","league":"Ancestor","id":"c4cf7cd0bb14347f23dbb8c8d0328f94147fdbcac0a4840d901e01f011fb45e7","sockets":[{"group":0,"attr":"S","sColour":"R"},{"group":0,"attr":"I","sColour":"B"},{"group":0,"attr":"S","sColour":"R"},{"group":0,"attr":"G","sColour":"W"},{"group":0,"attr":"G","sColour":"W"},{"group":1,"attr":"S","sColour":"R"}],"name":"Blunderbore","typeLine":"Astral Plate","baseType":"Astral Plate","identified":true,"ilvl":83,"properties":[{"name":"Quality","values":[["+20%",1]],"displayMode":0,"type":6},{"name":"Armour","values":[["1733",1]],"displayMode":0,"type":16}],"requirements":[{"name":"Level","values":[["62",0]],"displayMode":0,"type":62},{"name":"Str","values":[["804",1]],"displayMode":1,"type":63}],"implicitMods":["+12% to all Elemental Resistances"],"explicitMods":["+624 Strength Requirement","120% increased Armour","73% increased Effect of Shrine Buffs on you","You have Lesser Brutal Shrine Buff","You have Lesser Massive Shrine Buff"],"flavourText":["The giant cares not for the ants."],"frameType":3,"x":0,"y":0,"inventoryId":"BodyArmour","socketedItems":[]},{"verified":false,"w":2,"h":2,"icon":"https://web.poecdn.com/gen/image/WzI1LDE0LHsiZiI6IjJESXRlbXMvQXJtb3Vycy9IZWxtZXRzL0hlbG1ldFN0cjEwIiwidyI6MiwiaCI6Miwic2NhbGUiOjF9XQ/b1e95342a8/HelmetStr10.png","league":"Ancestor","id":"c156beb3b8ea368bd8cd4afbe55921d8cd183b2074df1552731e7d490e4aaeab","influences":{"elder":true},"elder":true,"sockets":[{"group":0,"attr":"S","sColour":"R"},{"group":0,"attr":"I","sColour":"B"}],"name":"Brimstone Ward","typeLine":"Royal Burgonet","baseType":"Royal Burgonet","identified":true,"ilvl":85,"properties":[{"name":"Quality","values":[["+29%",1]],"displayMode":0,"type":6},{"name":"Armour","values":[["641",1]],"displayMode":0,"type":16}],"requirements":[{"name":"Level","values":[["65",0]],"displayMode":0,"type":62},{"name":"Str","values":[["148",0]],"displayMode":1,"type":63}],"explicitMods":["Socketed Gems are Supported by Level 20 Immolate","Socketed Gems deal 30% more Elemental Damage","+76 to Armour","+89 to maximum Life","+9% to Fire Resistance","19% increased Ignite Duration on Enemies"],"frameType":2,"x":0,"y":0,"inventoryId":"Helm","socketedItems":[]}],"character":{"name":"Ten_Years_But_First_RF","realm":"pc","class":"Juggernaut","league":"Ancestor","level":100}}