{"total":15000,"cached_since":"2023-11-18T14:54:50+00:00","entries":[{"rank":11301,"dead":false,"public":true,"character":{"id":"38a9031c62a88acf773553be127d22ed85aecd4aeaedf6fd55de35f86f27cf97","name":"Disaster_ancestor","level":100,"class":"Necromancer","experience":4250334444,"depth":{"default":2,"solo":0},"ancestor":{"rank":546}},"account":{"name":"admiral_memes","realm":"pc","challenges":{"set":"Ancestral","completed":40,"max":40}}},{"rank":11302,"dead":false,"public":true,"character":{"id":"855ed4e951901cdd9f7a74d92c4f4d6fc8c589eb8d1b27221d8e581bb3e5065b","name":"GalãDasMina","level":100,"class":"Saboteur","experience":4250334444,"depth":{"default":106,"solo":106},"ancestor":{"rank":314}},"account":{"name":"Diguin","realm":"pc","challenges":{"set":"Ancestral","completed":13,"max":40},"twitch":{"name":"caiderano"}}},{"rank":11303,"dead":false,"public":true,"character":{"id":"e9a7bbbc169e59f895022873dcd5314d35827dceefd175c0e8681096d0d957b3","name":"Qeont","level":100,"class":"Saboteur","experience":4250334444,"ancestor":{"rank":2000}},"account":{"name":"qeon123","realm":"pc","challenges":{"set":"Ancestral","completed":9,"max":40},"twitch":{"name":"qeon9605"}}},{"rank":11304,"dead":false,"public":true,"character":{"id":"8dd758c760f6e21ae9960be94144fdea20d995fb7a0331a5e3ff8ff4e9786e0f","name":"Casually_c","level":100,"class":"Occultist","experience":4250334444,"depth":{"default":104,"solo":0},"ancestor":{"rank":481}},"account":{"name":"Ariceoy","realm":"pc","challenges":{"set":"Ancestral","completed":17,"max":40}}},{"rank":11305,"dead":false,"public":true,"character":{"id":"50fe92d865ac0f44da1855956b684125a5e67272476b33a51d07318edd299fe6","name":"Aluxysi","level":100,"class":"Elementalist","experience":4250334444,"depth":{"default":303,"solo":303},"ancestor":{"rank":748}},"account":{"name":"Japones","realm":"pc","challenges":{"set":"Ancestral","completed":38,"max":40},"twitch":{"name":"j4p0n3s"}}},{"rank":11306,"dead":false,"public":true,"character":{"id":"0f80b3d2ef13a60b07fa3f3c6b7bc3b69319c08584039bb861cb686635d23851","name":"Chroment","level":100,"class":"Ascendant","experience":4250334444},"account":{"name":"njdubs","realm":"pc","challenges":{"set":"Ancestral","completed":40,"max":40},"twitch":{"name":"wronsk0"}}},{"rank":11307,"dead":false,"public":true,"character":{"id":"dfab9bf8c1a91defb1add435c288a21888fc207ba095b313fedc30d509d3ad6f","name":"VASTOSS_AURA","level":100,"class":"Ascendant","experience":4250334444,"ancestor":{"rank":373}},"account":{"name":"Vastosss","realm":"pc","challenges":{"set":"Ancestral","completed":17,"max":40},"twitch":{"name":"vastossvas"}}},{"rank":11308,"dead":false,"public":true,"character":{"id":"9300cd701df7335e4d297cb526188389017f188125e2edaa869b3b530d228a68","name":"JKNewBie","level":100,"class":"Slayer","experience":4250334444,"depth":{"default":88,"solo":0},"ancestor":{"rank":193}},"account":{"name":"JKproKen","realm":"pc","challenges":{"set":"Ancestral","completed":17,"max":40},"twitch":{"name":"kenphams1"}}},{"rank":11309,"dead":false,"public":true,"character":{"id":"5461f65a80168ade4cbb22b9e1085e433298f64e5551bc494563e0d82dc8c2f9","name":"FaceTheArctic","level":100,"class":"Elementalist","experience":4250334444,"ancestor":{"rank":493}},"account":{"name":"FacesReality","realm":"pc","challenges":{"set":"Ancestral","completed":25,"max":40},"twitch":{"name":"facesreality"}}},{"rank":11310,"dead":false,"public":true,"character":{"id":"27fc441a4e3cdb3b79a151e4901742d39c96823ff5a9dd09c0b4d0a530fcf6d1","name":"lasomiredo","level":100,"class":"Necromancer","experience":4250334444,"ancestor":{"rank":2000}},"account":{"name":"souhang","realm":"pc","challenges":{"set":"Ancestral","completed":15,"max":40},"twitch":{"name":"lasomiredo"}}},{"rank":11311,"dead":false,"public":true,"character":{"id":"10a7d97a4e5503a78c4b37d88856cb2f08eca0596beb96d36be964f30b0abe4e","name":"RuepertGarf","level":100,"class":"Deadeye","experience":4250334444,"ancestor":{"rank":106}},"account":{"name":"IINTIMEZ","realm":"pc","challenges":{"set":"Ancestral","completed":14,"max":40},"twitch":{"name":"kkuarch"}}},{"rank":11312,"dead":false,"public":true,"character":{"id":"3433ac25dc6c80ccdf4811781c7e64ed4a090042c3277c1b33fc7ce1b3d9f7e6","name":"HoboChaosSkele","level":100,"class":"Necromancer","experience":4250334444,"ancestor":{"rank":368}},"account":{"name":"DarthAnakin","realm":"pc","challenges":{"set":"Ancestral","completed":25,"max":40},"twitch":{"name":"hobonator88"}}},{"rank":11313,"dead":false,"public":true,"character":{"id":"f863830cf61eb694c707b3f113bad4aa0cc07eec2d893d884b0eba760c3be791","name":"Ancestor_Zipher","level":100,"class":"Pathfinder","experience":4250334444,"depth":{"default":101,"solo":0},"ancestor":{"rank":1160}},"account":{"name":"TheZipher","realm":"pc","challenges":{"set":"Ancestral","completed":40,"max":40},"twitch":{"name":"thezipher1"}}},{"rank":11314,"dead":false,"character":{"id":"e553dd942f6050d3ea12ba427583b06391103b95f30de2ca8c51054f0933ae40","name":"NhoxLee","level":100,"class":"Berserker","experience":4250334444},"account":{"name":"nhoxsoi","realm":"pc","challenges":{"set":"Ancestral","completed":8,"max":40}}},{"rank":11315,"dead":false,"public":true,"character":{"id":"f437fe3c03de4212deeb687b19e53882bf435d4b7c262e0b920fa8554c3c88c9","name":"DyingIsForTheWEAK","level":100,"class":"Juggernaut","experience":4250334444,"depth":{"default":90,"solo":90},"ancestor":{"rank":177}},"account":{"name":"counterhitter402","realm":"pc","challenges":{"set":"Ancestral","completed":9,"max":40},"twitch":{"name":"counterhitter"}}},{"rank":11316,"dead":false,"character":{"id":"c32e0befb84cf74f318d293fc5d14b291a2455c844949798c3ec23430871f934","name":"FernandaMontenegro","level":100,"class":"Ascendant","experience":4250334444,"depth":{"default":103,"solo":0},"ancestor":{"rank":1203}},"account":{"name":"Barogue","realm":"pc","challenges":{"set":"Ancestral","completed":40,"max":40},"twitch":{"name":"o_famigerado_dan"}}},{"rank":11317,"dead":false,"public":true,"character":{"id":"2d509f297cc534aba0a239ec45cd8c24e2e4ac87cea7e963ee242c2aa6b055c1","name":"AzureRay_SauctumEnjoyer","level":100,"class":"Inquisitor","experience":4250334444,"ancestor":{"rank":154}},"account":{"name":"AdmiralKakaoO","realm":"pc","challenges":{"set":"Ancestral","completed":21,"max":40},"twitch":{"name":"barraquda_"}}},{"rank":11318,"dead":false,"character":{"id":"3c4936f5f8cc8c07399d133a0dabec316b08d44a148c1c79724a5adb085c92b9","name":"Kameli_BRRBRR","level":100,"class":"Deadeye","experience":4250334444,"ancestor":{"rank":137}},"account":{"name":"kassialma123","realm":"pc","challenges":{"set":"Ancestral","completed":16,"max":40},"twitch":{"name":"olkuuusa"}}},{"rank":11319,"dead":false,"public":true,"character":{"id":"0aac6683540fa746fff8a5f16936169f30d6a4285bca4f5fe4e0463aa5d61ba0","name":"Beidatass","level":100,"class":"Deadeye","experience":4250334444,"depth":{"default":103,"solo":0},"ancestor":{"rank":2000}},"account":{"name":"acrages","realm":"pc","challenges":{"set":"Ancestral","completed":32,"max":40},"twitch":{"name":"hawtfuzz"}}},{"rank":11320,"dead":false,"public":true,"character":{"id":"5594974ae005870295600a8c15f6170f7f33251ed2285519322a0fb79cae9e15","name":"iicicleMine","level":100,"class":"Deadeye","experience":4250334444,"depth":{"default":130,"solo":130},"ancestor":{"rank":339}},"account":{"name":"개곳수","realm":"pc","challenges":{"set":"Ancestral","completed":20,"max":40},"twitch":{"name":"jodaein"}}},{"rank":11321,"dead":false,"public":true,"character":{"id":"7cc53e7f9aae03890c839e4cf888dd1096051960c646da9e1c2e7e25b2b9cf78","name":"Wenndiekatze","level":100,"class":"Slayer","experience":4250334444},"account":{"name":"Psytanic","realm":"pc","challenges":{"set":"Ancestral","completed":10,"max":40},"twitch":{"name":"jaeguchi__"}}},{"rank":11322,"dead":false,"public":true,"character":{"id":"e2865c4ef832dea27d55795b6664d32bdb84d0a4cc401f501dd82008f50b4083","name":"DabbyT","level":100,"class":"Champion","experience":4250334444},"account":{"name":"mvporly86","realm":"pc","challenges":{"set":"Ancestral","completed":9,"max":40}}},{"rank":11323,"dead":false,"public":true,"character":{"id":"df9e69c427f3d9c35e1a6d499bad21ea5cdac60901ec38d5858f09c0b8acae35","name":"TabuLoop","level":100,"class":"Saboteur","experience":4250334444,"depth":{"default":2,"solo":0},"ancestor":{"rank":596}},"account":{"name":"KnaterFlater","realm":"pc","challenges":{"set":"Ancestral","completed":40,"max":40},"twitch":{"name":"heffalump89"}}},{"rank":11324,"dead":false,"public":true,"character":{"id":"a0d4ef6e4df5f8e62f03da6c8cca2a48ed7a9c3b3df304a761c3220e814d25c7","name":"CTRL_B","level":100,"class":"Deadeye","experience":4250334444,"depth":{"default":113,"solo":0},"ancestor":{"rank":662}},"account":{"name":"CTRLDDD","realm":"pc","challenges":{"set":"Ancestral","completed":40,"max":40},"twitch":{"name":"fea1838"}}},{"rank":11325,"dead":false,"public":true,"character":{"id":"33e0717a12f4d8676fc12bb85222dc2c1e56600aac7d520f7859ec0d2ab24d95","name":"ToastMiner","level":100,"class":"Saboteur","experience":4250334444,"ancestor":{"rank":612}},"account":{"name":"tomet","realm":"pc","challenges":{"set":"Ancestral","completed":40,"max":40},"twitch":{"name":"t045t3d"}}},{"rank":11326,"dead":false,"public":true,"character":{"id":"637838a4c62a0d0be5310f9af9796236898f524e72afc46f528264511fc58918","name":"Wasp_Ancestor","level":100,"class":"Elementalist","experience":4250334444},"account":{"name":"AKwasp","realm":"pc","challenges":{"set":"Ancestral","completed":7,"max":40},"twitch":{"name":"akwasp"}}},{"rank":11327,"dead":false,"public":true,"character":{"id":"97a5282a5ba02a65c3e47ffc724f196b35c1d298564a5ad3de961b21facd4b3d","name":"SlappinThemCheeks","level":100,"class":"Trickster","experience":4250334444,"depth":{"default":103,"solo":0},"ancestor":{"rank":378}},"account":{"name":"Mukuro123","realm":"pc","challenges":{"set":"Ancestral","completed":40,"max":40},"twitch":{"name":"xdcitrus"}}},{"rank":11328,"dead":false,"public":true,"character":{"id":"776392d3e879804f61c700bd82fc95236e0441a8f5b8d28500818fb2c4495f00","name":"DeleteMePlease","level":100,"class":"Pathfinder","experience":4250334444,"ancestor":{"rank":1393}},"account":{"name":"unitedx","realm":"pc","challenges":{"set":"Ancestral","completed":14,"max":40}}},{"rank":11329,"dead":false,"public":true,"character":{"id":"ee4e84125ba5f9b2221712a59fa35442c481a7e9725616a6ea8d90eb30bfe81d","name":"TBSXAncPsrs","level":100,"class":"Necromancer","experience":4250334444,"depth":{"default":2,"solo":0},"ancestor":{"rank":1100}},"account":{"name":"TrueBlueSX","realm":"pc","challenges":{"set":"Ancestral","completed":40,"max":40},"twitch":{"name":"truebluesx"}}},{"rank":11330,"dead":false,"public":true,"character":{"id":"68826a977cd19057e3053c555a3c302a0851df4a79f8f30d81b3d11faa7a5e3b","name":"ArtSmite","level":100,"class":"Chieftain","experience":4250334444},"account":{"name":"LordoDem","realm":"pc","challenges":{"set":"Ancestral","completed":17,"max":40},"twitch":{"name":"artomni"}}},{"rank":11331,"dead":false,"public":true,"character":{"id":"6254aafe1f804b36704e1e9978efea178d1746e46e5c0d985702d294f5252163","name":"LoveHug","level":100,"class":"Elementalist","experience":4250334444},"account":{"name":"DrowRRanger","realm":"pc","challenges":{"set":"Ancestral","completed":16,"max":40},"twitch":{"name":"bigorrr"}}},{"rank":11332,"dead":false,"character":{"id":"7eef5005152eaa038a80c3cfa5c6fdebea1e52ddfb1fa0f8f17b72e93db69123","name":"DankeyKongLong","level":100,"class":"Saboteur","experience":4250334444,"ancestor":{"rank":2000}},"account":{"name":"dankeykonguss","realm":"pc","challenges":{"set":"Ancestral","completed":16,"max":40}}},{"rank":11333,"dead":false,"public":true,"character":{"id":"57c23715337776fba8666cfd32f520b21d221c3cccd39447ac1be63c7f519487","name":"Bajrangi","level":100,"class":"Juggernaut","experience":4250334444,"depth":{"default":424,"solo":424},"ancestor":{"rank":449}},"account":{"name":"Naidu","realm":"pc","challenges":{"set":"Ancestral","completed":38,"max":40}}},{"rank":11334,"dead":false,"public":true,"character":{"id":"5fb0f0e2e2a09789d968d449361c528f312c409ea72b2f57f6a396c1eb06c19c","name":"Kulosaki","level":100,"class":"Necromancer","experience":4250334444},"account":{"name":"a1882090","realm":"pc","challenges":{"set":"Ancestral","completed":5,"max":40}}},{"rank":11335,"dead":false,"public":true,"character":{"id":"506871eacbd77b833768f2b653b3145a40e0d43ee73a04842c9e4ce3f567d2f6","name":"Nichqtp","level":100,"class":"Elementalist","experience":4250334444,"ancestor":{"rank":898}},"account":{"name":"nichqt","realm":"pc","challenges":{"set":"Ancestral","completed":18,"max":40}}},{"rank":11336,"dead":false,"public":true,"character":{"id":"c84ae81b79ef0c2d55b931cefbd39310da583d75b6df8b3b64a01f661acde602","name":"Aura_Aspect","level":100,"class":"Juggernaut","experience":4250334444,"depth":{"default":2,"solo":0},"ancestor":{"rank":229}},"account":{"name":"EnryuZahard","realm":"pc","challenges":{"set":"Ancestral","completed":16,"max":40}}},{"rank":11337,"dead":false,"public":true,"character":{"id":"df77e21742c08616a6f6dc46d8752771c8106a5b413206394f1f317e31a1e81f","name":"Vash_hotdog_slngn_carts","level":100,"class":"Hierophant","experience":4250334444,"depth":{"default":137,"solo":137},"ancestor":{"rank":434}},"account":{"name":"0011101001000100","realm":"pc","challenges":{"set":"Ancestral","completed":38,"max":40},"twitch":{"name":"vashthalas"}}},{"rank":11338,"dead":false,"public":true,"character":{"id":"176a601a5f9d402ab4b1f431b2e4e9ccc708fabb49e2099685df713f96969aac","name":"Tups","level":100,"class":"Champion","experience":4250334444,"depth":{"default":100,"solo":0},"ancestor":{"rank":2000}},"account":{"name":"Tupue","realm":"pc","challenges":{"set":"Ancestral","completed":15,"max":40}}},{"rank":11339,"dead":false,"public":true,"character":{"id":"2377dcc1169db9b47a6a06481f1ef806b70dbf4612d4ce8b99416b6afe3ef423","name":"AuthenticSanctum","level":100,"class":"Occultist","experience":4250334444},"account":{"name":"무성무성","realm":"pc","challenges":{"set":"Ancestral","completed":19,"max":40},"twitch":{"name":"peter0757"}}},{"rank":11340,"dead":false,"public":true,"character":{"id":"02036f07c16e1f2c7141939e401ff7ab95e84ac747ea935a5652a241baad53f2","name":"OkayBoomSC","level":100,"class":"Elementalist","experience":4250334444},"account":{"name":"Tadae23","realm":"pc","challenges":{"set":"Ancestral","completed":12,"max":40},"twitch":{"name":"itstadae"}}},{"rank":11341,"dead":false,"public":true,"character":{"id":"3280096fd11cff798dad88d91d7be07f9d2832c37cbc291feff630de01179876","name":"RailSparkInqCarry","level":100,"class":"Inquisitor","experience":4250334444,"depth":{"default":103,"solo":0},"ancestor":{"rank":232}},"account":{"name":"Railstin530","realm":"pc","challenges":{"set":"Ancestral","completed":40,"max":40},"twitch":{"name":"railstin"}}},{"rank":11342,"dead":false,"public":true,"character":{"id":"9353ecc87160b433d732383d5b978ca8171cb179627fb3fa797f5a95c651c185","name":"dadadadadaCATMAN","level":100,"class":"Saboteur","experience":4250334444,"depth":{"default":111,"solo":0},"ancestor":{"rank":469}},"account":{"name":"Smolz","realm":"pc","challenges":{"set":"Ancestral","completed":12,"max":40},"twitch":{"name":"smolzers"}}},{"rank":11343,"dead":false,"public":true,"character":{"id":"a67cbe41af1aff5fb3f3fcba9c8fa6f4eb9a79607685b7475e8c503f99daf686","name":"Excel_SWT","level":100,"class":"Hierophant","experience":4250334444,"ancestor":{"rank":577}},"account":{"name":"nyyron","realm":"pc","challenges":{"set":"Ancestral","completed":17,"max":40},"twitch":{"name":"nyyron"}}},{"rank":11344,"dead":false,"public":true,"character":{"id":"6a2d29abd90a6f0f4de98cb52b4187f4341e23b887cd68bbfbcb0820e5d5267d","name":"Ancestor_ToT","level":100,"class":"Hierophant","experience":4250334444,"depth":{"default":80,"solo":0},"ancestor":{"rank":1360}},"account":{"name":"엑_자_1","realm":"pc","challenges":{"set":"Ancestral","completed":13,"max":40},"twitch":{"name":"x4061x"}}},{"rank":11345,"dead":false,"public":true,"character":{"id":"b722a5d58d437fe9144f21cdf82e2a84db8bee4ebb415b582f6b396c7acfa598","name":"Ninjabunnies","level":100,"class":"Elementalist","experience":4250334444,"depth":{"default":104,"solo":0},"ancestor":{"rank":2000}},"account":{"name":"Ninjabunnies","realm":"pc","challenges":{"set":"Ancestral","completed":18,"max":40},"twitch":{"name":"ninjabunnies10000"}}},{"rank":11346,"dead":false,"character":{"id":"a62696cb52ad0bc13777ec81f8aa0db58e3925ca2ea49aea38bf6bec88559d16","name":"Simul_Slave","level":100,"class":"Necromancer","experience":4250334444},"account":{"name":"fyk4n","realm":"pc","challenges":{"set":"Ancestral","completed":6,"max":40}}},{"rank":11347,"dead":false,"public":true,"character":{"id":"0c6c31ba841a83b1afdee4b3b917573a215e942c34f1f2aaf9aeaea845e1bdc4","name":"Djwwpcrpmq","level":100,"class":"Elementalist","experience":4250334444,"depth":{"default":103,"solo":0},"ancestor":{"rank":499}},"account":{"name":"mimoza121","realm":"pc","challenges":{"set":"Ancestral","completed":23,"max":40},"twitch":{"name":"padre_228"}}},{"rank":11348,"dead":false,"public":true,"character":{"id":"fb885f676ef478aeac9f334361fbeecef64e81ed3313898206a7389fac1605ad","name":"Ancestor_Frozendead","level":100,"class":"Deadeye","experience":4250334444,"depth":{"default":103,"solo":0},"ancestor":{"rank":537}},"account":{"name":"Diablohan","realm":"pc","challenges":{"set":"Ancestral","completed":40,"max":40},"twitch":{"name":"diablohan"}}},{"rank":11349,"dead":false,"public":true,"character":{"id":"36b5f771c96763f951c3536e4be67ec18be78fa0dfa239b9c8de4168f39eacca","name":"盜墓者摸斗","level":100,"class":"Inquisitor","experience":4250334444,"ancestor":{"rank":421}},"account":{"name":"zxc0988451158","realm":"pc","challenges":{"set":"Ancestral","completed":16,"max":40},"twitch":{"name":"modopoe"}}},{"rank":11350,"dead":false,"character":{"id":"0e84450c5ec73e55620fb930cdfa9417fa3a1d9512ac7aba7994eb50b8494e65","name":"NQDGoo","level":100,"class":"Slayer","experience":4250334444,"ancestor":{"rank":255}},"account":{"name":"nhtl0257891","realm":"pc","challenges":{"set":"Ancestral","completed":10,"max":40}}},{"rank":11351,"dead":false,"public":true,"character":{"id":"bc6289c6869f8d02280c674f958bfe265fd296f5421f4d4d86d76002770e4145","name":"ZafiAnce","level":100,"class":"Deadeye","experience":4250334444,"depth":{"default":102,"solo":0},"ancestor":{"rank":751}},"account":{"name":"Zafirho","realm":"pc","challenges":{"set":"Ancestral","completed":40,"max":40},"twitch":{"name":"zafhiro28"}}},{"rank":11352,"dead":false,"public":true,"character":{"id":"1419efa5aa678edcdf6af54fd572a8e504deae9e63d0d1d27bf6bc80a34ff271","name":"AightningLrrowAlice","level":100,"class":"Deadeye","experience":4250334444,"depth":{"default":102,"solo":0},"ancestor":{"rank":2000}},"account":{"name":"1074346716","realm":"pc","challenges":{"set":"Ancestral","completed":40,"max":40}}},{"rank":11353,"dead":false,"public":true,"character":{"id":"24886ba0207f995da51a115b92061c315a4b4fa8ea470b21107f248d0abc88c3","name":"แก๊งค์เด็กข้างไข่","level":100,"class":"Elementalist","experience":4250334444,"ancestor":{"rank":2000}},"account":{"name":"HoFa2Ra","realm":"pc","challenges":{"set":"Ancestral","completed":19,"max":40},"twitch":{"name":"minseedsa01"}}},{"rank":11354,"dead":false,"public":true,"character":{"id":"29d14fc183350b7ef849ca1c27637bbb327829fcafc7acea3b718844ed16f90b","name":"HexSaboteur","level":100,"class":"Saboteur","experience":4250334444,"depth":{"default":94,"solo":0},"ancestor":{"rank":470}},"account":{"name":"TheBarnicle","realm":"pc","challenges":{"set":"Ancestral","completed":23,"max":40},"twitch":{"name":"barneymadlad"}}},{"rank":11355,"dead":false,"public":true,"character":{"id":"da3e597d2c62f9b2bdb2d151fb20d6de6bbfa677282a803cf4a99a13b79a5383","name":"Watameismyoshi","level":100,"class":"Pathfinder","experience":4250334444,"ancestor":{"rank":127}},"account":{"name":"Krenìs","realm":"pc","challenges":{"set":"Ancestral","completed":17,"max":40},"twitch":{"name":"xkrenis"}}},{"rank":11356,"dead":false,"public":true,"character":{"id":"0a12a531a5dd34057002c29e8dcb49695113f794550abe47b113dce8588f6d43","name":"TOTAlNooblet","level":100,"class":"Deadeye","experience":4250334444,"depth":{"default":2,"solo":0},"ancestor":{"rank":793}},"account":{"name":"s0lidchef","realm":"pc","challenges":{"set":"Ancestral","completed":38,"max":40},"twitch":{"name":"fottagogast"}}},{"rank":11357,"dead":false,"public":true,"character":{"id":"8d828f73f0b963ffcdfef5abc5b9907287a3ae09e8406fe209858abf48acfaff","name":"HED_TA_K","level":100,"class":"Occultist","experience":4250334444,"ancestor":{"rank":145}},"account":{"name":"0486","realm":"pc","challenges":{"set":"Ancestral","completed":40,"max":40},"twitch":{"name":"wweenn82"}}},{"rank":11358,"dead":false,"public":true,"character":{"id":"10efd3b32936c708dc09f639110d61dd0c87da68971f2db7209c4abf9d4b5f7e","name":"avanto_olento","level":100,"class":"Juggernaut","experience":4250334444,"depth":{"default":103,"solo":0},"ancestor":{"rank":489}},"account":{"name":"Jaltsi","realm":"pc","challenges":{"set":"Ancestral","completed":25,"max":40},"twitch":{"name":"jaltsi"}}},{"rank":11359,"dead":false,"public":true,"character":{"id":"d22d9b19dbf830dc4d6f3fccff646c64ef10b6ac1bfae038a01c1cb56cb7b3fd","name":"MaecrowCest","level":100,"class":"Deadeye","experience":4250334444,"depth":{"default":110,"solo":110},"ancestor":{"rank":2000}},"account":{"name":"Maecrow","realm":"pc","challenges":{"set":"Ancestral","completed":16,"max":40}}},{"rank":11360,"dead":false,"character":{"id":"97501ffa73071f0b0a6ef55dd9524a248cb70dd85743dbefb995fd141731471d","name":"pewpewewpewp","level":100,"class":"Champion","experience":4250334444,"depth":{"default":18,"solo":0},"ancestor":{"rank":361}},"account":{"name":"xuanhuu","realm":"pc","challenges":{"set":"Ancestral","completed":40,"max":40},"twitch":{"name":"huutranxuan95"}}},{"rank":11361,"dead":false,"public":true,"character":{"id":"a5465385c23e46ecfc2ab911e37e4e589cc1e009c071e6f6ff5d725f162439e3","name":"WiggleHisslehoff","level":100,"class":"Ascendant","experience":4250334444},"account":{"name":"PiperFawn","realm":"pc","challenges":{"set":"Ancestral","completed":9,"max":40}}},{"rank":11362,"dead":false,"public":true,"character":{"id":"82555180e0f0a12acc51e8be90e2cc7e74ce8bf6921266de2e226a920e62e9a2","name":"sirdooch","level":100,"class":"Trickster","experience":4250334444,"depth":{"default":67,"solo":0},"ancestor":{"rank":293}},"account":{"name":"girflove","realm":"pc","challenges":{"set":"Ancestral","completed":12,"max":40}}},{"rank":11363,"dead":false,"public":true,"character":{"id":"f8b9e98b71aa85f70d9f21a9dfc48fc274a6015079d52927442111fb7846a10a","name":"OsweGOAT","level":100,"class":"Champion","experience":4250334444,"depth":{"default":47,"solo":0},"ancestor":{"rank":2000}},"account":{"name":"OswegoTV","realm":"pc","challenges":{"set":"Ancestral","completed":12,"max":40},"twitch":{"name":"oswegotv"}}},{"rank":11364,"dead":false,"public":true,"character":{"id":"95738cf00be42f4ede632cab34bc0ac69c5b1b5aceaabab8fe5d9f7ed4836739","name":"유비는귀가큽니다","level":100,"class":"Occultist","experience":4250334444,"ancestor":{"rank":517}},"account":{"name":"aivori7","realm":"pc","challenges":{"set":"Ancestral","completed":16,"max":40},"twitch":{"name":"goldfg"}}},{"rank":11365,"dead":false,"public":true,"character":{"id":"7e2a9283bcf45fa270e42f23cc4b7841984b3d39b212080fb0bb7daca74ccc63","name":"exsangkite","level":100,"class":"Pathfinder","experience":4250334444,"depth":{"default":101,"solo":0},"ancestor":{"rank":552}},"account":{"name":"Lobsterkite","realm":"pc","challenges":{"set":"Ancestral","completed":38,"max":40},"twitch":{"name":"lobsterkite"}}},{"rank":11366,"dead":false,"public":true,"character":{"id":"9fa77eb00725889c6a95eb63dc2030c0415d3954eadcda785e92e581645cf4f4","name":"MuddTank","level":100,"class":"Chieftain","experience":4250334444,"ancestor":{"rank":1794}},"account":{"name":"muddzlinga","realm":"pc","challenges":{"set":"Ancestral","completed":9,"max":40},"twitch":{"name":"muddzlinga"}}},{"rank":11367,"dead":false,"public":true,"character":{"id":"b6e09ca5d7afc111ecfe95720534e483548a61fd29db3c165606aa7401f73e3a","name":"Ancestor_CKB","level":100,"class":"Berserker","experience":4250334444,"ancestor":{"rank":157}},"account":{"name":"Aventier","realm":"pc","challenges":{"set":"Ancestral","completed":37,"max":40}}},{"rank":11368,"dead":false,"public":true,"character":{"id":"02fbac65eae46c0029d04872fe7fc2a903ea986bba2e35a22cb5df3fabedc6e8","name":"YoungSisicTraper","level":100,"class":"Deadeye","experience":4250334444,"ancestor":{"rank":265}},"account":{"name":"JoraPOEMaster","realm":"pc","challenges":{"set":"Ancestral","completed":22,"max":40}}},{"rank":11369,"dead":false,"public":true,"character":{"id":"1f0258d6f47803167a78ddb6c3a475b701f25f0aba2980b89788a11a5633939b","name":"cortsabo","level":100,"class":"Saboteur","experience":4250334444,"depth":{"default":104,"solo":0},"ancestor":{"rank":505}},"account":{"name":"cortleng","realm":"pc","challenges":{"set":"Ancestral","completed":17,"max":40},"twitch":{"name":"cortleng"}}},{"rank":11370,"dead":false,"public":true,"character":{"id":"c963be92fe44a87274e9dea5e470efb768a6be8868c722f684bf70a61c8a3a0f","name":"KiborgUbiza","level":100,"class":"Occultist","experience":4250334444,"depth":{"default":307,"solo":307},"ancestor":{"rank":254}},"account":{"name":"FiascoBrat","realm":"pc","challenges":{"set":"Ancestral","completed":13,"max":40},"twitch":{"name":"masafaka77"}}},{"rank":11371,"dead":false,"public":true,"character":{"id":"60dddc1e80c83a67ec1d00db3a93bcaae058d8ea24d969bb45c28a35af901eb0","name":"BdubzToTA","level":100,"class":"Juggernaut","experience":4250334444,"ancestor":{"rank":2000}},"account":{"name":"bdubz55","realm":"pc","challenges":{"set":"Ancestral","completed":19,"max":40},"twitch":{"name":"bdubz404"}}},{"rank":11372,"dead":false,"public":true,"character":{"id":"8e89b1dbad02e3dced15524c5721ef2a9172447aa096ea01cd1bca443ae8e972","name":"jazz_AlwaysRerollsPfff","level":100,"class":"Chieftain","experience":4250334444,"depth":{"default":606,"solo":606},"ancestor":{"rank":175}},"account":{"name":"qorrr","realm":"pc","challenges":{"set":"Ancestral","completed":18,"max":40},"twitch":{"name":"jazzqor"}}},{"rank":11373,"dead":false,"public":true,"character":{"id":"05f3de5f53da8e3fdfb360513daefe99a96d1394c5e2ec8e02b755bbae7f4cff","name":"Ancestor_Gulingling","level":100,"class":"Deadeye","experience":4250334444,"ancestor":{"rank":2000}},"account":{"name":"ppazzyy","realm":"pc","challenges":{"set":"Ancestral","completed":12,"max":40}}},{"rank":11374,"dead":false,"public":true,"character":{"id":"8d107132cced0ad90aac3d794f942ed15c509179dc8e4cf42044685797e577bb","name":"InsikTS","level":100,"class":"Deadeye","experience":4250334444,"depth":{"default":2,"solo":0},"ancestor":{"rank":283}},"account":{"name":"Insik6","realm":"pc","challenges":{"set":"Ancestral","completed":38,"max":40},"twitch":{"name":"insikd"}}},{"rank":11375,"dead":false,"public":true,"character":{"id":"7c5f5bd8c27850d64f5b0938576b1d5269648b648f8ad4e6afbbdd96886721ac","name":"ReqTrial","level":100,"class":"Pathfinder","experience":4250334444,"depth":{"default":242,"solo":242},"ancestor":{"rank":746}},"account":{"name":"Requiral","realm":"pc","challenges":{"set":"Ancestral","completed":40,"max":40},"twitch":{"name":"requiral"}}},{"rank":11376,"dead":false,"public":true,"character":{"id":"b47c153f0ea56828bfe270b037690672ffab1681408a7ca3e22bab7ceb595baf","name":"๏Ancestor๏Farming๏","level":100,"class":"Occultist","experience":4250334444,"ancestor":{"rank":293}},"account":{"name":"hoang4341","realm":"pc","challenges":{"set":"Ancestral","completed":40,"max":40},"twitch":{"name":"hoang4341"}}},{"rank":11377,"dead":false,"public":true,"character":{"id":"faced33dedd2638b068ef3427d07091293bacd5a1ffbd4989ccd93fdeef0d3bd","name":"선조_콩쥐","level":100,"class":"Raider","experience":4250334444,"depth":{"default":103,"solo":0},"ancestor":{"rank":519}},"account":{"name":"콩쥐팥쥐","realm":"pc","challenges":{"set":"Ancestral","completed":40,"max":40},"twitch":{"name":"ritual_kongji"}}},{"rank":11378,"dead":false,"public":true,"character":{"id":"3319ed977a43fc6bd99dbd7a8a0509419a2d2e3fe986f8b042c32f5509228f58","name":"thorphin","level":100,"class":"Deadeye","experience":4250334444,"ancestor":{"rank":2000}},"account":{"name":"hikman","realm":"pc","challenges":{"set":"Ancestral","completed":18,"max":40},"twitch":{"name":"yupania"}}},{"rank":11379,"dead":false,"public":true,"character":{"id":"81b60a8e5b5c2d293783df655ae35a7ccb6b0edde421c17198f7c203774c77cf","name":"Funguscranium","level":100,"class":"Hierophant","experience":4250334444,"ancestor":{"rank":232}},"account":{"name":"surdburger","realm":"pc","challenges":{"set":"Ancestral","completed":13,"max":40}}},{"rank":11380,"dead":false,"public":true,"character":{"id":"01b63b6229442bfaaf45b7a0c11456a3ca79faf7557e323b2e562f40ec3fa0d5","name":"EURO_TH","level":100,"class":"Pathfinder","experience":4250334444,"depth":{"default":144,"solo":144},"ancestor":{"rank":325}},"account":{"name":"JAVeieiTH","realm":"pc","challenges":{"set":"Ancestral","completed":40,"max":40}}},{"rank":11381,"dead":false,"public":true,"character":{"id":"e10a25e7fb662aef6eb0e6f45c094e1430a7f8ac199ee8dbfd316303f9e1596e","name":"Meuaurameabandonou","level":100,"class":"Deadeye","experience":4250334444,"depth":{"default":108,"solo":0},"ancestor":{"rank":2000}},"account":{"name":"iveshenrique","realm":"pc","challenges":{"set":"Ancestral","completed":20,"max":40}}},{"rank":11382,"dead":false,"public":true,"character":{"id":"283c36430e7399de2633b46bf270abc0dbaa51fe5cee70c1a9e6927f01b64ee0","name":"wokkopf","level":100,"class":"Pathfinder","experience":4250334444,"depth":{"default":43,"solo":0},"ancestor":{"rank":217}},"account":{"name":"Nerfmalte","realm":"pc","challenges":{"set":"Ancestral","completed":18,"max":40},"twitch":{"name":"nerfmalte1"}}},{"rank":11383,"dead":false,"public":true,"character":{"id":"86ac04db5477c7934f8c301311231ea76aa08001e0a15709ad2ab70b0c953c9b","name":"你就是个金箔","level":100,"class":"Elementalist","experience":4250334444,"ancestor":{"rank":1524}},"account":{"name":"HMPpPPP","realm":"pc","challenges":{"set":"Ancestral","completed":19,"max":40}}},{"rank":11384,"dead":false,"public":true,"character":{"id":"549ac3c21cd5e8d559cb3b680e343d25a2c2751d0f263a9a91f10d4a5981dc7b","name":"핵블지_망했냐","level":100,"class":"Saboteur","experience":4250334444,"depth":{"default":2,"solo":0},"ancestor":{"rank":657}},"account":{"name":"김헌병","realm":"pc","challenges":{"set":"Ancestral","completed":40,"max":40},"twitch":{"name":"riglog"}}},{"rank":11385,"dead":false,"public":true,"character":{"id":"0946125f678a7112f4aeffdc6eb1ae479b4ef3375cbe4660cc150f045073ef40","name":"OmniRoyal","level":100,"class":"Ascendant","experience":4250334444},"account":{"name":"RoyalNZ","realm":"pc","challenges":{"set":"Ancestral","completed":40,"max":40}}},{"rank":11386,"dead":false,"public":true,"character":{"id":"d2fe79630766d4d3792ffd87ed3b5ca278bdf4cbef2c7a4bf21ab06f14130ca1","name":"LuckyHoneyPot","level":100,"class":"Deadeye","experience":4250334444},"account":{"name":"GuessWhoBB","realm":"pc","challenges":{"set":"Ancestral","completed":12,"max":40}}},{"rank":11387,"dead":false,"public":true,"character":{"id":"957d3c73dc4416412b32411f29b4e5a4cd9f777b6c13f349f677402fa66276c4","name":"Ancestor_mamong","level":100,"class":"Occultist","experience":4250334444,"depth":{"default":2,"solo":0},"ancestor":{"rank":529}},"account":{"name":"Lucky__strike","realm":"pc","challenges":{"set":"Ancestral","completed":40,"max":40},"twitch":{"name":"lucky_st"}}},{"rank":11388,"dead":false,"public":true,"character":{"id":"281b40b3e683a09f1d9b4ef7fa49ba21ece39fb30964da27b60cb1b13585c27c","name":"AllthePrettyHorses","level":100,"class":"Champion","experience":4250334444,"depth":{"default":208,"solo":208},"ancestor":{"rank":374}},"account":{"name":"amoureuses","realm":"pc","challenges":{"set":"Ancestral","completed":14,"max":40},"twitch":{"name":"amoureuses"}}},{"rank":11389,"dead":false,"public":true,"character":{"id":"b23a0d2917de98f51d36b4f007099e93943de6163189f9281ae38b7688b5e086","name":"Fivewayrain","level":100,"class":"Deadeye","experience":4250334444},"account":{"name":"a188209000","realm":"pc","challenges":{"set":"Ancestral","completed":5,"max":40},"twitch":{"name":"a188209000"}}},{"rank":11390,"dead":false,"public":true,"character":{"id":"db952ce24075d0263913fb411308dd67ab7bd50acf9c1a3b181fcb3ea264b29a","name":"Heavenly_Seraphime","level":100,"class":"Ascendant","experience":4250334444,"depth":{"default":2,"solo":0},"ancestor":{"rank":314}},"account":{"name":"Ruin_Trinity","realm":"pc","challenges":{"set":"Ancestral","completed":40,"max":40},"twitch":{"name":"x_shadowkill626_x"}}},{"rank":11391,"dead":false,"public":true,"character":{"id":"7a76c50f31541e0bd3b313abf8d75aba57421d017f25495d30dec1f476c769a7","name":"DJ_SODA","level":100,"class":"Trickster","experience":4250334444,"depth":{"default":103,"solo":0},"ancestor":{"rank":972}},"account":{"name":"mantake","realm":"pc","challenges":{"set":"Ancestral","completed":40,"max":40},"twitch":{"name":"cwewqdsax"}}},{"rank":11392,"dead":false,"public":true,"character":{"id":"87527df0d86a245ce7d7cd77e9330f0dc5f1680a098a72f197a282e2f507f193","name":"RF_FireTrap_Trial","level":100,"class":"Inquisitor","experience":4250334444,"depth":{"default":515,"solo":515},"ancestor":{"rank":385}},"account":{"name":"Kintay","realm":"pc","challenges":{"set":"Ancestral","completed":38,"max":40},"twitch":{"name":"ryk3"}}},{"rank":11393,"dead":false,"public":true,"character":{"id":"2e2b77cbea46e19aef3acd810c64da44d6f25d70e366258c74c10d54664236c2","name":"Enjoy_the_Silence_","level":100,"class":"Inquisitor","experience":4250334444,"depth":{"default":323,"solo":323},"ancestor":{"rank":1078}},"account":{"name":"MrDragos","realm":"pc","challenges":{"set":"Ancestral","completed":40,"max":40},"twitch":{"name":"mr_gold_"}}},{"rank":11394,"dead":false,"public":true,"character":{"id":"f807aac668d296cd34305d47cf83d22c1d4fd0d8fbd1a20db6794e234d9a7f58","name":"블리자드이렇게해야지","level":100,"class":"Trickster","experience":4250334444,"ancestor":{"rank":325}},"account":{"name":"ipoetodelve","realm":"pc","challenges":{"set":"Ancestral","completed":37,"max":40},"twitch":{"name":"valosopher"}}},{"rank":11395,"dead":false,"public":true,"character":{"id":"4d0131e071a19ea40e0e1e90a4f5580f3afa3ed9a4db4560033a5df1a36b7478","name":"Bee_Sparker","level":100,"class":"Inquisitor","experience":4250334444},"account":{"name":"beechance","realm":"pc","challenges":{"set":"Ancestral","completed":7,"max":40},"twitch":{"name":"bechan22"}}},{"rank":11396,"dead":false,"public":true,"character":{"id":"054f8d864cb789b9a577aa0e6acb020d00f07a1f315fc927b39ba68357ad547d","name":"Nev_anc","level":100,"class":"Trickster","experience":4250334444,"depth":{"default":86,"solo":0},"ancestor":{"rank":445}},"account":{"name":"Nevskiyy","realm":"pc","challenges":{"set":"Ancestral","completed":17,"max":40}}},{"rank":11397,"dead":false,"public":true,"character":{"id":"a9a71d411c82006684721574e12e1c077bb5db9639aa995938478b3afdab61aa","name":"Horse_Hooves","level":100,"class":"Elementalist","experience":4250334444,"ancestor":{"rank":2000}},"account":{"name":"Shawntastic69","realm":"pc","challenges":{"set":"Ancestral","completed":18,"max":40},"twitch":{"name":"gachi_mundo"}}},{"rank":11398,"dead":false,"public":true,"character":{"id":"988fab9b05c078d3b250ed2a8d73809203ad68cc3eb9193557defb65351bba85","name":"Ancestor_Enchant","level":100,"class":"Juggernaut","experience":4250334444,"ancestor":{"rank":229}},"account":{"name":"끼일이","realm":"pc","challenges":{"set":"Ancestral","completed":40,"max":40}}},{"rank":11399,"dead":false,"public":true,"character":{"id":"d27607be714c2c75d5881163cf317020d6721119625c890da9246c567aaa3667","name":"Tunnaz","level":100,"class":"Deadeye","experience":4250334444,"depth":{"default":101,"solo":0},"ancestor":{"rank":525}},"account":{"name":"Tonydinh","realm":"pc","challenges":{"set":"Ancestral","completed":40,"max":40}}},{"rank":11400,"dead":false,"public":true,"character":{"id":"06921c22aac571cab75e26a23542552633a9d441d809e92ab9f739c6754d4f2a","name":"TomorrowIWillHaveLunch","level":100,"class":"Juggernaut","experience":4250334444},"account":{"name":"TomMastery","realm":"pc","challenges":{"set":"Ancestral","completed":5,"max":40}}}]}